[
  {
    "id": "greek",
    "category": "pantheon",
    "name": { "zh": "希腊神话", "en": "Greek Mythology" },
    "shortName": { "zh": "希腊", "en": "Greek" },
    "region": { "zh": "爱琴海与地中海", "en": "Aegean & Mediterranean" },
    "period": { "zh": "约公元前8世纪起", "en": "from c. 8th century BCE" },
    "anchor": { "lat": 38.5, "lon": 23.5 },
    "countries": [300, 196],
    "color": "#b08d57"
  },
  {
    "id": "norse",
    "category": "pantheon",
    "name": { "zh": "北欧神话", "en": "Norse Mythology" },
    "shortName": { "zh": "北欧", "en": "Norse" },
    "region": { "zh": "斯堪的纳维亚", "en": "Scandinavia" },
    "period": { "zh": "维京时代，成书于13世纪", "en": "Viking Age, written down 13th century" },
    "anchor": { "lat": 61.0, "lon": 9.0 },
    "countries": [578, 752, 208, 352],
    "color": "#6e7f8d"
  },
  {
    "id": "celtic",
    "category": "pantheon",
    "name": { "zh": "凯尔特神话", "en": "Celtic Mythology" },
    "shortName": { "zh": "凯尔特", "en": "Celtic" },
    "region": { "zh": "爱尔兰与不列颠", "en": "Ireland & Britain" },
    "period": { "zh": "铁器时代起，成书于中世纪", "en": "Iron Age origins, medieval manuscripts" },
    "anchor": { "lat": 53.4, "lon": -7.9 },
    "countries": [372, 826],
    "color": "#5a7d5a"
  },
  {
    "id": "slavic",
    "category": "pantheon",
    "name": { "zh": "斯拉夫神话", "en": "Slavic Mythology" },
    "shortName": { "zh": "斯拉夫", "en": "Slavic" },
    "region": { "zh": "东欧与巴尔干", "en": "Eastern Europe & Balkans" },
    "period": { "zh": "基督教化前，约6至12世纪", "en": "pre-Christian, c. 6th–12th century" },
    "anchor": { "lat": 50.4, "lon": 30.5 },
    "countries": [643, 804, 616, 112, 203, 703, 688, 100, 191],
    "color": "#8a6d3b"
  },
  {
    "id": "egyptian",
    "category": "pantheon",
    "name": { "zh": "埃及神话", "en": "Egyptian Mythology" },
    "shortName": { "zh": "埃及", "en": "Egyptian" },
    "region": { "zh": "尼罗河流域", "en": "Nile Valley" },
    "period": { "zh": "约公元前3100年起", "en": "from c. 3100 BCE" },
    "anchor": { "lat": 26.8, "lon": 30.8 },
    "countries": [818],
    "color": "#c2a14d"
  },
  {
    "id": "mesopotamian",
    "category": "pantheon",
    "name": { "zh": "两河神话", "en": "Mesopotamian Mythology" },
    "shortName": { "zh": "两河", "en": "Mesopotamian" },
    "region": { "zh": "底格里斯与幼发拉底河之间", "en": "Between the Tigris & Euphrates" },
    "period": { "zh": "约公元前3000年起", "en": "from c. 3000 BCE" },
    "anchor": { "lat": 32.5, "lon": 44.4 },
    "countries": [368, 760],
    "color": "#a2683a"
  },
  {
    "id": "persian",
    "category": "pantheon",
    "name": { "zh": "波斯神话", "en": "Persian Mythology" },
    "shortName": { "zh": "波斯", "en": "Persian" },
    "region": { "zh": "伊朗高原", "en": "Iranian Plateau" },
    "period": { "zh": "琐罗亚斯德教传统，约公元前1000年起", "en": "Zoroastrian tradition, from c. 1000 BCE" },
    "anchor": { "lat": 32.4, "lon": 53.7 },
    "countries": [364],
    "color": "#4f6d9e"
  },
  {
    "id": "hindu",
    "category": "pantheon",
    "name": { "zh": "印度神话", "en": "Hindu Mythology" },
    "shortName": { "zh": "印度", "en": "Hindu" },
    "region": { "zh": "南亚次大陆", "en": "Indian Subcontinent" },
    "period": { "zh": "吠陀时代起，约公元前1500年", "en": "from the Vedic period, c. 1500 BCE" },
    "anchor": { "lat": 25.3, "lon": 83.0 },
    "countries": [356, 524, 144],
    "color": "#c26e38"
  },
  {
    "id": "chinese",
    "category": "pantheon",
    "name": { "zh": "华夏神话", "en": "Chinese Mythology" },
    "shortName": { "zh": "华夏", "en": "Chinese" },
    "region": { "zh": "黄河与长江流域", "en": "Yellow & Yangtze River Valleys" },
    "period": { "zh": "上古传说时代起", "en": "from legendary antiquity" },
    "anchor": { "lat": 34.5, "lon": 110.0 },
    "countries": [156, 158],
    "color": "#9e3b33"
  },
  {
    "id": "japanese",
    "category": "pantheon",
    "name": { "zh": "日本神话", "en": "Japanese Mythology" },
    "shortName": { "zh": "日本", "en": "Japanese" },
    "region": { "zh": "日本列岛", "en": "Japanese Archipelago" },
    "period": { "zh": "《古事记》成书于712年", "en": "Kojiki compiled 712 CE" },
    "anchor": { "lat": 36.5, "lon": 138.5 },
    "countries": [392],
    "color": "#7c6a8e"
  },
  {
    "id": "korean",
    "category": "pantheon",
    "name": { "zh": "朝鲜半岛神话", "en": "Korean Mythology" },
    "shortName": { "zh": "朝鲜半岛", "en": "Korean" },
    "region": { "zh": "朝鲜半岛", "en": "Korean Peninsula" },
    "period": { "zh": "檀君传说，约公元前2333年", "en": "Dangun legend, trad. 2333 BCE" },
    "anchor": { "lat": 37.5, "lon": 127.0 },
    "countries": [410, 408],
    "color": "#4a7a74"
  },
  {
    "id": "abrahamic",
    "category": "pantheon",
    "name": { "zh": "圣经传统", "en": "Biblical Tradition" },
    "shortName": { "zh": "圣经", "en": "Biblical" },
    "region": { "zh": "黎凡特", "en": "The Levant" },
    "period": { "zh": "希伯来圣经成书于公元前一千纪", "en": "Hebrew Bible, 1st millennium BCE" },
    "anchor": { "lat": 31.8, "lon": 35.2 },
    "countries": [376, 275, 400, 422],
    "color": "#8a8a5a"
  },
  {
    "id": "arabian",
    "category": "pantheon",
    "name": { "zh": "阿拉伯传说", "en": "Arabian Lore" },
    "shortName": { "zh": "阿拉伯", "en": "Arabian" },
    "region": { "zh": "阿拉伯半岛", "en": "Arabian Peninsula" },
    "period": { "zh": "前伊斯兰时代至《一千零一夜》", "en": "pre-Islamic era to the Thousand and One Nights" },
    "anchor": { "lat": 23.5, "lon": 45.0 },
    "countries": [682, 887, 512, 784],
    "color": "#3f7a6e"
  },
  {
    "id": "yoruba",
    "category": "pantheon",
    "name": { "zh": "约鲁巴神话", "en": "Yoruba Mythology" },
    "shortName": { "zh": "约鲁巴", "en": "Yoruba" },
    "region": { "zh": "西非几内亚湾", "en": "West Africa, Gulf of Guinea" },
    "period": { "zh": "口传传统，伊费古城约11世纪", "en": "oral tradition, Ife flourished c. 11th century" },
    "anchor": { "lat": 7.5, "lon": 4.6 },
    "countries": [566, 204, 768],
    "color": "#4a5d8a"
  },
  {
    "id": "aztec",
    "category": "pantheon",
    "name": { "zh": "阿兹特克神话", "en": "Aztec Mythology" },
    "shortName": { "zh": "阿兹特克", "en": "Aztec" },
    "region": { "zh": "墨西哥谷地", "en": "Valley of Mexico" },
    "period": { "zh": "14至16世纪", "en": "14th–16th century" },
    "anchor": { "lat": 19.4, "lon": -99.1 },
    "countries": [484],
    "color": "#3f7a5c"
  },
  {
    "id": "maya",
    "category": "pantheon",
    "name": { "zh": "玛雅神话", "en": "Maya Mythology" },
    "shortName": { "zh": "玛雅", "en": "Maya" },
    "region": { "zh": "尤卡坦与中美洲", "en": "Yucatán & Mesoamerica" },
    "period": { "zh": "约公元前2000年起，《波波尔·乌》成书于16世纪", "en": "from c. 2000 BCE, Popol Vuh written 16th century" },
    "anchor": { "lat": 17.2, "lon": -89.6 },
    "countries": [320, 84, 340],
    "color": "#2e8577"
  },
  {
    "id": "inca",
    "category": "pantheon",
    "name": { "zh": "印加神话", "en": "Inca Mythology" },
    "shortName": { "zh": "印加", "en": "Inca" },
    "region": { "zh": "安第斯山脉", "en": "The Andes" },
    "period": { "zh": "13至16世纪", "en": "13th–16th century" },
    "anchor": { "lat": -13.5, "lon": -72.0 },
    "countries": [604, 68, 218],
    "color": "#a98436"
  },
  {
    "id": "native-american",
    "category": "pantheon",
    "name": { "zh": "北美原住民神话", "en": "Native American Mythology" },
    "shortName": { "zh": "北美原住民", "en": "Native American" },
    "region": { "zh": "北美大陆", "en": "North America" },
    "period": { "zh": "口传传统，绵延数千年", "en": "oral traditions spanning millennia" },
    "anchor": { "lat": 46.0, "lon": -105.0 },
    "countries": [840, 124],
    "color": "#8c5a3c"
  },
  {
    "id": "polynesian",
    "category": "pantheon",
    "name": { "zh": "波利尼西亚神话", "en": "Polynesian Mythology" },
    "shortName": { "zh": "波利尼西亚", "en": "Polynesian" },
    "region": { "zh": "太平洋群岛", "en": "Pacific Islands" },
    "period": { "zh": "口传传统，随航海扩散", "en": "oral traditions spread by voyagers" },
    "anchor": { "lat": -17.5, "lon": -149.5 },
    "countries": [554, 242, 882, 776, 258],
    "color": "#2f6f8f"
  },
  {
    "id": "aboriginal",
    "category": "pantheon",
    "name": { "zh": "澳洲原住民神话", "en": "Aboriginal Australian Mythology" },
    "shortName": { "zh": "澳洲原住民", "en": "Aboriginal" },
    "region": { "zh": "澳大利亚", "en": "Australia" },
    "period": { "zh": "梦创时代，口传逾数万年", "en": "the Dreaming, oral traditions tens of millennia old" },
    "anchor": { "lat": -25.3, "lon": 131.0 },
    "countries": [36],
    "color": "#9c5a38"
  },
  {
    "id": "inuit",
    "category": "pantheon",
    "name": { "zh": "因纽特神话", "en": "Inuit Mythic Traditions" },
    "shortName": { "zh": "因纽特", "en": "Inuit" },
    "region": { "zh": "北美极地与格陵兰", "en": "Arctic North America & Greenland" },
    "period": { "zh": "跨极地口传传统，19世纪起系统记录", "en": "circumpolar oral traditions, systematically recorded from the 19th century" },
    "anchor": { "lat": 69.2, "lon": -72.0 },
    "countries": [124, 304, 840],
    "color": "#6b9da3"
  },
  {
    "id": "philippine",
    "category": "pantheon",
    "name": { "zh": "菲律宾群岛神话", "en": "Myths of the Philippine Archipelago" },
    "shortName": { "zh": "菲律宾群岛", "en": "Philippine" },
    "region": { "zh": "吕宋、米沙鄢与棉兰老", "en": "Luzon, Visayas & Mindanao" },
    "period": { "zh": "前殖民口传至当代民间信仰", "en": "precolonial oral traditions to living folklore" },
    "anchor": { "lat": 12.4, "lon": 122.1 },
    "countries": [608],
    "color": "#b56b4c"
  },
  {
    "id": "akan",
    "category": "pantheon",
    "name": { "zh": "阿坎神话", "en": "Akan Mythic Tradition" },
    "shortName": { "zh": "阿坎", "en": "Akan" },
    "region": { "zh": "加纳与科特迪瓦南部", "en": "Southern Ghana & Côte d’Ivoire" },
    "period": { "zh": "活态口传传统，17世纪起见于文字记录", "en": "living oral tradition, recorded in writing from the 17th century" },
    "anchor": { "lat": 6.7, "lon": -1.5 },
    "countries": [288, 384],
    "color": "#c08a3e"
  },
  {
    "id": "guarani",
    "category": "pantheon",
    "name": { "zh": "瓜拉尼神话", "en": "Guaraní Mythic Traditions" },
    "shortName": { "zh": "瓜拉尼", "en": "Guaraní" },
    "region": { "zh": "巴拉圭河流域与南美低地", "en": "Paraguay Basin & South American lowlands" },
    "period": { "zh": "活态口传与圣歌传统，16世纪起见于文字记录", "en": "living oral and sacred-song traditions, recorded from the 16th century" },
    "anchor": { "lat": -24.2, "lon": -56.4 },
    "countries": [600, 32, 76, 68],
    "color": "#4f8a68"
  },
  {
    "id": "shanhaijing",
    "category": "classic",
    "name": { "zh": "山海经", "en": "Classic of Mountains and Seas" },
    "shortName": { "zh": "山海经", "en": "Shanhaijing" },
    "region": { "zh": "上古中国的山川四海", "en": "Mountains and seas of ancient China" },
    "period": { "zh": "战国至西汉成书", "en": "compiled Warring States to Western Han" },
    "anchor": { "lat": 36.5, "lon": 87.0 },
    "countries": [156],
    "color": "#7a3b2e"
  },
  {
    "id": "kaidan",
    "category": "urban",
    "name": { "zh": "日本怪谈", "en": "Japanese Kaidan & Urban Legends" },
    "shortName": { "zh": "日式怪谈", "en": "Kaidan" },
    "region": { "zh": "日本", "en": "Japan" },
    "period": { "zh": "江户怪谈至网络时代", "en": "Edo-period kaidan to the internet age" },
    "anchor": { "lat": 33.5, "lon": 134.0 },
    "countries": [392],
    "color": "#4b3f6b"
  },
  {
    "id": "american-folklore",
    "category": "urban",
    "name": { "zh": "美洲怪谈", "en": "American Folklore & Cryptids" },
    "shortName": { "zh": "美式怪谈", "en": "Americana" },
    "region": { "zh": "北美洲", "en": "North America" },
    "period": { "zh": "殖民时代传说至网络怪谈", "en": "colonial-era legends to internet horror" },
    "anchor": { "lat": 38.9, "lon": -82.1 },
    "countries": [840, 124],
    "color": "#52705f"
  },
  {
    "id": "lost-lands",
    "category": "lostland",
    "name": { "zh": "失落之地", "en": "Lost Lands" },
    "shortName": { "zh": "失落之地", "en": "Lost Lands" },
    "region": { "zh": "传说中沉没与隐匿的国度", "en": "Sunken and hidden realms of legend" },
    "period": { "zh": "自柏拉图记述至近代神秘学", "en": "from Plato's account to modern esoterica" },
    "anchor": { "lat": 33.0, "lon": -35.0 },
    "countries": [],
    "color": "#35637c"
  }
]
